{
  "length": 4000,
  "playerStart": { "x": 80, "y": 300 },
  "endZone": { "x": 3800, "y": 480, "w": 20, "h": 60 },
  "platforms": [
    [0, 500, 300, 40],
    [400, 500, 150, 40], 
    [650, 400, 250, 40],
    [1000, 350, 80, 20],
    [1150, 300, 80, 20],
    [1300, 250, 80, 20],
    [1500, 500, 400, 40],
    [2100, 400, 100, 40],
    [2350, 500, 500, 40],
    [3000, 450, 100, 20],
    [3200, 400, 100, 20],
    [3400, 350, 100, 20],
    [3600, 500, 400, 40]
  ],
  "enemies": [
    { "type": "drink", "x": 200, "y": 460, "w": 20, "h": 20 },
    { "type": "drink", "x": 500, "y": 460, "w": 20, "h": 20 },
    { "type": "drink", "x": 750, "y": 360, "w": 20, "h": 20 },
    { "type": "drink", "x": 1050, "y": 330, "w": 20, "h": 20 },
    { "type": "drink", "x": 1600, "y": 460, "w": 20, "h": 20 },
    { "type": "drink", "x": 2150, "y": 360, "w": 20, "h": 20 },
    { "type": "drink", "x": 2500, "y": 460, "w": 20, "h": 20 },
    { "type": "drink", "x": 2750, "y": 460, "w": 20, "h": 20 },
    { "type": "drink", "x": 3650, "y": 460, "w": 20, "h": 20 },
    
    // Cuori Aggiunti
    { "type": "heart", "x": 450, "y": 400, "w": 20, "h": 20 },
    { "type": "heart", "x": 1200, "y": 200, "w": 20, "h": 20 },
    { "type": "heart", "x": 2250, "y": 300, "w": 20, "h": 20 },
    { "type": "heart", "x": 3300, "y": 250, "w": 20, "h": 20 }
  ],
  "invisible_traps": [
    { "type": "fall_death", "x": 300, "y": 540, "w": 100, "h": 100 },
    { "type": "fall_death", "x": 1900, "y": 540, "w": 200, "h": 100 },
    { "type": "fall_death", "x": 2850, "y": 540, "w": 150, "h": 100 }
  ]
}
